hop3_tui/__init__.py
hop3_tui/__main__.py
hop3_tui/app.py
hop3_tui/config.py
hop3_tui/api/__init__.py
hop3_tui/api/client.py
hop3_tui/api/models.py
hop3_tui/screens/__init__.py
hop3_tui/screens/addons.py
hop3_tui/screens/app_detail.py
hop3_tui/screens/apps.py
hop3_tui/screens/backups.py
hop3_tui/screens/chat.py
hop3_tui/screens/dashboard.py
hop3_tui/screens/env_vars.py
hop3_tui/screens/logs.py
hop3_tui/screens/processes.py
hop3_tui/screens/system.py
hop3_tui/screens/system_logs.py
hop3_tui/styles/base.tcss
hop3_tui/widgets/__init__.py
hop3_tui/widgets/confirmation.py
hop3_tui/widgets/status_badge.py
hop3_tui/widgets/status_panel.py
hop3_tui-0.4.0b1.dist-info/METADATA
hop3_tui-0.4.0b1.dist-info/WHEEL
hop3_tui-0.4.0b1.dist-info/entry_points.txt
hop3_tui-0.4.0b1.dist-info/RECORD
